ades/__init__.py
ades/_version.py
ades/adesutility.py
ades/applyxslt
ades/convertutility.py
ades/getencoding
ades/jsontoxml.py
ades/maketexfiles
ades/mpc80coltoxml.py
ades/packUtil.py
ades/psvtoxml.py
ades/readxmlpy.py
ades/sexVals.py
ades/testit.py
ades/unittest
ades/valades.py
ades/valall.py
ades/valgeneral.py
ades/validate.py
ades/valsubmit.py
ades/valutility.py
ades/writexml
ades/writexmlpy
ades/xmltojson.py
ades/xmltompc80col.py
ades/xmltopsv.py
ades/xmlutility.py
ades/xxx80y.py
ades/data/xml/adesmaster.xml
ades/data/xsd/general.xsd
ades/data/xsd/submit.xsd
ades/data/xslt/latex/docades.xslt
ades/data/xslt/latex/docelementstable.xslt
ades/data/xslt/latex/docgrouptypestable.xslt
ades/data/xslt/latex/docsimpletypestable.xslt
ades/data/xslt/util/tableades.xslt
ades/data/xslt/xsd/distribhumanxsd.xslt
ades/data/xslt/xsd/distribxsd.xslt
ades/data/xslt/xsd/generalhumanxsd.xslt
ades/data/xslt/xsd/generalxsd.xslt
ades/data/xslt/xsd/submithumanxsd.xslt
ades/data/xslt/xsd/submitxsd.xslt
ades/data/xslt/xsd.old/distribhumanxsd.xslt
ades/data/xslt/xsd.old/distribxsd.xslt
ades/data/xslt/xsd.old/generalhumanxsd.xslt
ades/data/xslt/xsd.old/generalxsd.xslt
ades/data/xslt/xsd.old/submithumanxsd.xslt
ades/data/xslt/xsd.old/submitxsd.xslt
iau_ades-0.1.1.dist-info/METADATA
iau_ades-0.1.1.dist-info/WHEEL
iau_ades-0.1.1.dist-info/entry_points.txt
iau_ades-0.1.1.dist-info/top_level.txt
iau_ades-0.1.1.dist-info/RECORD
