Metadata-Version: 2.4
Name: iau-ades
Version: 0.1.1
Requires-Dist: json5
Requires-Dist: lxml
Requires-Dist: xmltodict
Requires-Dist: pyyaml
Provides-Extra: test
Requires-Dist: pytest; extra == "test"
